curvefitgui/__init__.py
curvefitgui/_curvefitgui.py
curvefitgui/_gui.py
curvefitgui/_qt_compat.py
curvefitgui/_settings.py
curvefitgui/_tools.py
curvefitgui/_version.py
curvefitgui/_widgets.py
curvefitgui/config.txt
curvefitgui-1.2.0.dist-info/licenses/LICENSE.txt
curvefitgui-1.2.0.dist-info/METADATA
curvefitgui-1.2.0.dist-info/WHEEL
curvefitgui-1.2.0.dist-info/top_level.txt
curvefitgui-1.2.0.dist-info/RECORD
