Metadata-Version: 2.4
Name: curvefitgui
Version: 1.2.0
Summary: GUI for the scipy.optimize.curve_fit() function
Home-page: https://github.com/moosepy/curvefitgui
Author: moosepy
Author-email: moose_dev@icloud.com
License: MIT
Classifier: License :: OSI Approved :: MIT License
Classifier: Programming Language :: Python :: 3
Classifier: Operating System :: OS Independent
Requires-Python: >=3.7, <4
License-File: LICENSE.txt
Dynamic: author
Dynamic: author-email
Dynamic: classifier
Dynamic: description
Dynamic: description-content-type
Dynamic: home-page
Dynamic: license
Dynamic: license-file
Dynamic: requires-python
Dynamic: summary
